bistiming/__init__.py
bistiming/multistopwatch.py
bistiming/stopwatch.py
bistiming/tests/__init__.py
bistiming/tests/test_multistopwatch.py
bistiming/tests/test_stopwatch.py
bistiming/tests/utils.py
bistiming/utils.py
bistiming-0.5.1.post0.dist-info/LICENSE
bistiming-0.5.1.post0.dist-info/METADATA
bistiming-0.5.1.post0.dist-info/WHEEL
bistiming-0.5.1.post0.dist-info/RECORD
