Metadata-Version: 2.1
Name: bistiming
Version: 0.5.1.post0
Summary: A logging-friendly stopwatch and profiling tool for Python.
Home-page: https://bistiming.readthedocs.io
License: MIT
Author: Ian Lin
Author-email: you@example.com
Requires-Python: >=3.7,<4.0
Classifier: License :: OSI Approved :: MIT License
Classifier: Programming Language :: Python :: 3
Classifier: Programming Language :: Python :: 3.7
Classifier: Programming Language :: Python :: 3.8
Classifier: Programming Language :: Python :: 3.9
Classifier: Programming Language :: Python :: 3.10
Classifier: Programming Language :: Python :: 3.11
Classifier: Programming Language :: Python :: 3.12
Classifier: Programming Language :: Python :: 3.13
Classifier: Topic :: Utilities
Requires-Dist: importlib-metadata ; python_version < "3.8"
Requires-Dist: six (>=1.12,<2.0)
Requires-Dist: tabulate (>=0.9,<0.10)
Project-URL: Repository, https://github.com/ianlini/bistiming
